webmon/__init__.py
webmon/_version.py
webmon/main.py
webmon/utils.py
webmon-0.0.7.dist-info/DESCRIPTION.rst
webmon-0.0.7.dist-info/entry_points.txt
webmon-0.0.7.dist-info/METADATA
webmon-0.0.7.dist-info/metadata.json
webmon-0.0.7.dist-info/RECORD
webmon-0.0.7.dist-info/top_level.txt
webmon-0.0.7.dist-info/WHEEL
