Metadata-Version: 2.0
Name: webmon
Version: 0.0.7
Summary: Monitor websites for visual changes
Home-page: https://github.com/mc706/webmon
Author: Ryan McDevitt
Author-email: mcdevitt.ryan@gmail.com
License: MIT License
Download-URL: https://github.com/mc706/webmon/tarball0.0
Keywords: web monitoring,screenshots,website diff
Platform: UNKNOWN
Classifier: Programming Language :: Python :: 2.6
Classifier: Programming Language :: Python :: 2.7
Classifier: Programming Language :: Python :: 3
Classifier: Development Status :: 2 - Pre-Alpha
Classifier: Environment :: Console
Classifier: Intended Audience :: Developers
Classifier: Intended Audience :: Information Technology
Classifier: License :: OSI Approved :: MIT License
Classifier: Operating System :: OS Independent
Classifier: Topic :: Communications :: Email
Classifier: Topic :: Software Development :: Testing
Classifier: Topic :: Utilities
Requires-Dist: click
Requires-Dist: configparser
Requires-Dist: Pillow
Requires-Dist: splinter
Requires-Dist: colorama
